starlette_jhalog/__init__.py
starlette_jhalog/_exceptions.py
starlette_jhalog/_middleware.py
starlette_jhalog/py.typed
starlette_jhalog-0.1.4.dist-info/LICENSE
starlette_jhalog-0.1.4.dist-info/WHEEL
starlette_jhalog-0.1.4.dist-info/METADATA
starlette_jhalog-0.1.4.dist-info/RECORD
